resvg-0.1.2.dist-info/METADATA
resvg-0.1.2.dist-info/WHEEL
resvg-0.1.2.dist-info/license_files/LICENSE.txt
resvg/__init__.py
resvg/resvg.cpython-310-darwin.so
resvg-0.1.2.dist-info/RECORD
