Metadata-Version: 2.1
Name: resvg
Version: 0.1.2
Classifier: Programming Language :: Rust
Classifier: Programming Language :: Python :: Implementation :: CPython
Classifier: Programming Language :: Python :: Implementation :: PyPy
License-File: LICENSE.txt
Summary: A Python binding of resvg, the high-performance SVG rendering library in Rust
Keywords: 
Author-email: Brice Yan <briceyan3.0@gmail.com>
License: MIT
Requires-Python: >=3.8
